{
  "version": "7",
  "dialect": "postgresql",
  "entries": [
    {
      "idx": 0,
      "version": "7",
      "when": 1754459916365,
      "tag": "0000_charming_lilandra",
      "breakpoints": true
    },
    {
      "idx": 1,
      "version": "7",
      "when": 1754460033106,
      "tag": "0001_lean_black_widow",
      "breakpoints": true
    },
    {
      "idx": 2,
      "version": "7",
      "when": 1754589135770,
      "tag": "0002_fluffy_charles_xavier",
      "breakpoints": true
    },
    {
      "idx": 3,
      "version": "7",
      "when": 1754896804956,
      "tag": "0003_bizarre_wraith",
      "breakpoints": true
    },
    {
      "idx": 4,
      "version": "7",
      "when": 1755002351741,
      "tag": "0004_bouncy_kinsey_walden",
      "breakpoints": true
    }
  ]
}